grash/__init__.py
grash/console.py
grash/graph.py
grash/parser.py
grash-0.1.1.dist-info/entry_points.txt
grash-0.1.1.dist-info/LICENSE
grash-0.1.1.dist-info/WHEEL
grash-0.1.1.dist-info/METADATA
grash-0.1.1.dist-info/RECORD
