Metadata-Version: 2.1
Name: grash
Version: 0.1.1
Summary: A dependency analysis tool for bash scripts
Author: Colin McAllister
Author-email: colinmca242@gmail.com
Requires-Python: >=3.6,<4.0
Classifier: Programming Language :: Python :: 3
Classifier: Programming Language :: Python :: 3.6
Classifier: Programming Language :: Python :: 3.7
Classifier: Programming Language :: Python :: 3.8
Classifier: Programming Language :: Python :: 3.9
Requires-Dist: bashlex (>=0.15,<0.16)
Requires-Dist: python-magic (>=0.4.20,<0.5.0)
